funhouse/__init__.py
funhouse/core.py
funhouse/technical.py
funhouse-0.1.8.dist-info/DESCRIPTION.rst
funhouse-0.1.8.dist-info/METADATA
funhouse-0.1.8.dist-info/RECORD
funhouse-0.1.8.dist-info/WHEEL
funhouse-0.1.8.dist-info/metadata.json
funhouse-0.1.8.dist-info/top_level.txt
